[
    {
        "Repo-Name": "FYC's Pirated Repos",
        "Movies": {
            "FTUApps.com] - Internet Download Manager (IDM) 6.41 Build 7 Multilingual Portable": {
                "Name": "FTUApps.com] - Internet Download Manager (IDM) 6.41 Build 7 Multilingual Portable",
                ".Torrent": "http://itorrents.org/torrent/F30BDDE848304994B19FE8DC2D735820DE228526.torrent",
                "MagnetUrl": "magnet:?xt=urn:btih:6MF532CIGBEZJMM75DOC242YEDPCFBJG&dn=%5BFTUApps.com%5D%20-%20Internet%20Download%20Manager%20(IDM)%206.41%20Build%207%20Multilingual%20Portable&tr=udp%3A%2F%2Ftracker.leechers-paradise.org%3A6969%2Fannounce",
                "Icon": "https://github.com/HttpAnimation/FYC-Rewrite-V2/blob/main/PFP_1704426442876.png?raw=true",
                "HasStreamURL": false,
                "StreamURL": "stream.mp4"
            }
        }
    }
]